MANIFEST.in
README.txt
setup.cfg
setup.py
Products/__init__.py
Products.galleriffic.egg-info/PKG-INFO
Products.galleriffic.egg-info/SOURCES.txt
Products.galleriffic.egg-info/dependency_links.txt
Products.galleriffic.egg-info/entry_points.txt
Products.galleriffic.egg-info/namespace_packages.txt
Products.galleriffic.egg-info/not-zip-safe
Products.galleriffic.egg-info/requires.txt
Products.galleriffic.egg-info/top_level.txt
Products/galleriffic/__init__.py
Products/galleriffic/browser.py
Products/galleriffic/configure.zcml
Products/galleriffic/interfaces.py
Products/galleriffic/setuphandlers.py
Products/galleriffic/tests.py
Products/galleriffic/view.py
Products/galleriffic/locales/Products.galleriffic.pot
Products/galleriffic/locales/en/LC_MESSAGES/Products.galleriffic.mo
Products/galleriffic/locales/en/LC_MESSAGES/Products.galleriffic.po
Products/galleriffic/locales/it/LC_MESSAGES/Products.galleriffic.mo
Products/galleriffic/locales/it/LC_MESSAGES/Products.galleriffic.po
Products/galleriffic/portlets/__init__.py
Products/galleriffic/portlets/configure.zcml
Products/galleriffic/portlets/galleriffic_portlet.pt
Products/galleriffic/portlets/galleriffic_portlet.py
Products/galleriffic/profiles/default/actions.xml
Products/galleriffic/profiles/default/browserlayer.xml
Products/galleriffic/profiles/default/cssregistry.xml
Products/galleriffic/profiles/default/import_steps.xml
Products/galleriffic/profiles/default/jsregistry.xml
Products/galleriffic/profiles/default/metadata.xml
Products/galleriffic/profiles/default/portlets.xml
Products/galleriffic/profiles/default/skins.xml
Products/galleriffic/skins/.DS_Store
Products/galleriffic/skins/abstract_galleriffic_images/lightbox-blank.gif
Products/galleriffic/skins/abstract_galleriffic_images/lightbox-btn-close.gif
Products/galleriffic/skins/abstract_galleriffic_images/lightbox-btn-next.gif
Products/galleriffic/skins/abstract_galleriffic_images/lightbox-btn-prev.gif
Products/galleriffic/skins/abstract_galleriffic_images/lightbox-ico-loading.gif
Products/galleriffic/skins/abstract_galleriffic_images/loader.gif
Products/galleriffic/skins/abstract_galleriffic_styles/galleriffic.css
Products/galleriffic/skins/abstract_galleriffic_styles/jq.galleriffic.init.js
Products/galleriffic/skins/abstract_galleriffic_styles/jq.galleriffic.js
