Metadata-Version: 1.0
Name: Products.galleriffic
Version: 1.0.5
Summary: A gallery view with galleriffic script
Home-page: http://www.abstract.it
Author: Luca Pisani
Author-email: luca.pisani@abstract.it
License: GPL
Keywords: galleriffic abstract portlet view
Platform: UNKNOWN
Classifier: Programming Language :: Python
